quantum_launcher/__init__.py
quantum_launcher/exceptions.py
quantum_launcher/utils.py
quantum_launcher/base/__init__.py
quantum_launcher/base/adapter_structure.py
quantum_launcher/base/base.py
quantum_launcher/base/translator.py
quantum_launcher/hampy/__init__.py
quantum_launcher/hampy/debug.py
quantum_launcher/hampy/equations.py
quantum_launcher/hampy/object.py
quantum_launcher/hampy/utils.py
quantum_launcher/launcher/__init__.py
quantum_launcher/launcher/aql.py
quantum_launcher/launcher/profiling_launcher.py
quantum_launcher/launcher/qlauncher.py
quantum_launcher/problems/__init__.py
quantum_launcher/problems/problem_formulations/__init__.py
quantum_launcher/problems/problem_formulations/bqm.py
quantum_launcher/problems/problem_formulations/hamiltonian.py
quantum_launcher/problems/problem_formulations/qubo.py
quantum_launcher/problems/problem_formulations/hamiltonians/__init__.py
quantum_launcher/problems/problem_formulations/hamiltonians/tsp.py
quantum_launcher/problems/problem_formulations/jssp/Binary.py
quantum_launcher/problems/problem_formulations/jssp/__init__.py
quantum_launcher/problems/problem_formulations/jssp/pyqubo_scheduler.py
quantum_launcher/problems/problem_formulations/jssp/qiskit_scheduler.py
quantum_launcher/problems/problem_formulations/jssp/scheduler.py
quantum_launcher/problems/problem_initialization/__init__.py
quantum_launcher/problems/problem_initialization/ec.py
quantum_launcher/problems/problem_initialization/graph_coloring.py
quantum_launcher/problems/problem_initialization/jssp.py
quantum_launcher/problems/problem_initialization/maxcut.py
quantum_launcher/problems/problem_initialization/qatm.py
quantum_launcher/problems/problem_initialization/raw.py
quantum_launcher/problems/problem_initialization/tsp.py
quantum_launcher/routines/__init__.py
quantum_launcher/routines/cirq_routines.py
quantum_launcher/routines/dwave_routines.py
quantum_launcher/routines/orca_routines.py
quantum_launcher/routines/qiskit_routines/__init__.py
quantum_launcher-2.0.4.dist-info/licenses/LICENSE
quantum_launcher-2.0.4.dist-info/METADATA
quantum_launcher-2.0.4.dist-info/WHEEL
quantum_launcher-2.0.4.dist-info/top_level.txt
quantum_launcher-2.0.4.dist-info/RECORD
