Metadata-Version: 2.4
Name: quantum-launcher
Version: 2.0.4
Summary: Quantum Launcher is modular tool, for solving many problems on many algorithms using many quantum computing backends
Requires-Python: >=3.11
License-File: LICENSE
Requires-Dist: networkx
Requires-Dist: notebook
Requires-Dist: numpy<=1.26.4
Requires-Dist: overrides
Requires-Dist: pandas
Requires-Dist: matplotlib
Requires-Dist: pyqubo
Requires-Dist: scipy
Requires-Dist: qiskit
Requires-Dist: qiskit_algorithms
Requires-Dist: qiskit_aqt_provider
Requires-Dist: qiskit_ibm_runtime
Requires-Dist: qiskit_optimization
Requires-Dist: qiskit_aer
Requires-Dist: qcg-pilotjob
Requires-Dist: dill
Provides-Extra: orca
Requires-Dist: numba==0.60.0; extra == "orca"
Requires-Dist: torch; extra == "orca"
Provides-Extra: dwave
Requires-Dist: dwave-ocean-sdk; extra == "dwave"
Requires-Dist: dwave-tabu>=0.5.0; extra == "dwave"
Provides-Extra: cirq
Requires-Dist: cirq>=1.4.1; extra == "cirq"
Requires-Dist: ply; extra == "cirq"
Provides-Extra: dev
Requires-Dist: pytest; extra == "dev"
Requires-Dist: pytest-httpx>=0.35.0; extra == "dev"
Dynamic: license-file
